{
  "users": [
    {
      "id": "123",
      "city": "Truckee, California",
      "first_name": "Andrew",
      "last_name": "Maclean",
      "email": "andrew.n.maclean@gmail.com",
      "bio": "Something about Andrew Maclean",
      "activity_count": "10",
      "friend_count": "5",
      "images": [],
      "activities": [
        {
          "creator_id": "123",
          "adventure_name": "Old Adventure",
          "adventure_type": "ski",
          "nearest_city": "Truckee, California",
          "adventure_id": "789"
        }
      ],
      "ticks": [
        {
          "user_id": "123",
          "adventure_name": "New Adventure",
          "adventure_type": "ski",
          "adventure_id": "456",
          "nearest_city": "Truckee, California"
        }
      ],
      "friends": [
        {
          "id": "456",
          "first_name": "Jamie",
          "last_name": "Anderson",
          "email": "jamie@email.com"
        }
      ]
    },
    {
      "id": "446",
      "city": "San Francisco, California",
      "first_name": "Jamie",
      "last_name": "Anderson",
      "email": "jamie@email.com",
      "bio": "Something Jamie likes to do. I guess she snowboards a bunch.",
      "activity_count": "12",
      "friend_count": "450",
      "images": [],
      "activites": [],
      "ticks": [],
      "friends": [
        {
          "id": "123",
          "first_name": "Andrew",
          "last_name": "Maclean",
          "email": "andrew.n.maclean@gmail.com"
        }
      ]
    }
  ]
}
